stb/image.cpython-37m-x86_64-linux-gnu.so
stbpy-0.0.5.dist-info/top_level.txt
stbpy-0.0.5.dist-info/WHEEL
stbpy-0.0.5.dist-info/RECORD
stbpy-0.0.5.dist-info/METADATA
