Metadata-Version: 2.1
Name: stbpy
Version: 0.0.5
Summary: Cython wrapper for nothings/stb
Home-page: https://github.com/aforren1/stbpy
Author: Alex Forrence
Author-email: alex.forrence@gmail.com
License: UNKNOWN
Platform: UNKNOWN
Classifier: Programming Language :: Python :: 3
Classifier: License :: OSI Approved :: MIT License
Classifier: Operating System :: OS Independent
